Metadata-Version: 2.4
Name: adafruit-circuitpython-veml7700
Version: 2.1.6
Summary: CircuitPython driver for VEML7700 high precision I2C ambient light sensor.
Author-email: Adafruit Industries <circuitpython@adafruit.com>
License: MIT
Project-URL: Homepage, https://github.com/adafruit/Adafruit_CircuitPython_VEML7700
Keywords: adafruit,blinka,circuitpython,micropython,veml7700,ambient,light,sensor,i2c,precision
Classifier: Intended Audience :: Developers
Classifier: Topic :: Software Development :: Libraries
Classifier: Topic :: Software Development :: Embedded Systems
Classifier: Topic :: System :: Hardware
Classifier: License :: OSI Approved :: MIT License
Classifier: Programming Language :: Python :: 3
License-File: LICENSE
Requires-Dist: Adafruit-Blinka
Requires-Dist: adafruit-circuitpython-register
Requires-Dist: adafruit-circuitpython-busdevice
Dynamic: license-file
